cf/__init__.py
cf/__main__.py
cf/blog.py
cf/bloguser.py
cf/classes.py
cf/compare.py
cf/contest_list.py
cf/conteststatus.py
cf/problems.py
cf/ratingchange.py
cf/user_info.py
cf/user_rating.py
cf/userstatus.py
cf/util.py
pythoncf-1.1.2.dist-info/LICENSE
pythoncf-1.1.2.dist-info/METADATA
pythoncf-1.1.2.dist-info/WHEEL
pythoncf-1.1.2.dist-info/entry_points.txt
pythoncf-1.1.2.dist-info/top_level.txt
pythoncf-1.1.2.dist-info/RECORD
