Metadata-Version: 2.1
Name: pythoncf
Version: 1.1.2
Summary: `pythoncf` is your command-line companion for all things Codeforces.
Home-page: https://github.com/Sudhir878786/pythoncf
Author: Sudhir_Sharma
Author-email: sudhirsharma@iitbhilai.ac.in
License: MIT
Keywords: Codeforces,cli,command line,terminal
Requires: requests
Requires: prettytable
Requires: bs4
Requires: colorama
Requires: numpy
Requires: mdv
Requires: html2text
Requires: gnuplotlib
Requires: termgraph
Requires: yaspin
Requires-Python: >=3.6
License-File: LICENSE
Requires-Dist: requests
Requires-Dist: prettytable
Requires-Dist: bs4
Requires-Dist: colorama
Requires-Dist: numpy
Requires-Dist: mdv
Requires-Dist: html2text
Requires-Dist: gnuplotlib
Requires-Dist: termgraph
Requires-Dist: yaspin
